aiaim/__init__.py
aiaim/agent_cli.py
aiaim/cli.py
aiaim/session.py
aiaim/supervisor.py
aiaim/task_runner.py
aiaim/worker.py
aiaim-0.2.0.dist-info/METADATA
aiaim-0.2.0.dist-info/WHEEL
aiaim-0.2.0.dist-info/entry_points.txt
aiaim-0.2.0.dist-info/top_level.txt
aiaim-0.2.0.dist-info/RECORD
