Metadata-Version: 2.4
Name: aiaim
Version: 0.2.0
Summary: AI Agent Iterative Manager - Supervisor/Worker agent pattern for task completion
Author: aiaim contributors
License: MIT
Project-URL: Homepage, https://github.com/aiaim/aiaim
Project-URL: Repository, https://github.com/aiaim/aiaim
Keywords: ai,agent,supervisor,worker,task,automation,cursor
Classifier: Development Status :: 3 - Alpha
Classifier: Intended Audience :: Developers
Classifier: License :: OSI Approved :: MIT License
Classifier: Programming Language :: Python :: 3
Classifier: Programming Language :: Python :: 3.9
Classifier: Programming Language :: Python :: 3.10
Classifier: Programming Language :: Python :: 3.11
Classifier: Programming Language :: Python :: 3.12
Classifier: Topic :: Software Development :: Libraries :: Python Modules
Requires-Python: >=3.9
Requires-Dist: click>=8.0.0
Requires-Dist: pydantic>=2.0.0
Requires-Dist: rich>=13.0.0
Provides-Extra: dev
Requires-Dist: pytest>=7.0.0; extra == "dev"
Requires-Dist: pytest-asyncio>=0.21.0; extra == "dev"
Requires-Dist: black>=23.0.0; extra == "dev"
Requires-Dist: ruff>=0.1.0; extra == "dev"
